postman_github_sync/__init__.py
postman_github_sync/helper_functions.py
postman_github_sync/main.py
postman_github_sync-0.1.0.3.dist-info/METADATA
postman_github_sync-0.1.0.3.dist-info/WHEEL
postman_github_sync-0.1.0.3.dist-info/entry_points.txt
postman_github_sync-0.1.0.3.dist-info/top_level.txt
postman_github_sync-0.1.0.3.dist-info/RECORD
