Metadata-Version: 2.1
Name: postman_github_sync
Version: 0.1.0.3
Summary: This script automates the process of setting up GitHub Actions workflows for Postman collections. It supports both GitHub repository integration and local workflow setup, allowing for flexible usage in various scenarios.
Home-page: https://github.com/BlazinArtemis/postman_to_github_actions
Author: Oluwaseyi Ajadi
Author-email: oluwaseyinexus137@gmail.com
Classifier: Development Status :: 3 - Alpha
Classifier: Intended Audience :: Developers
Classifier: License :: OSI Approved :: MIT License
Classifier: Operating System :: OS Independent
Requires-Python: >=3.7
Requires-Dist: requests==2.31.0
Requires-Dist: urllib3==2.0.7
Requires-Dist: chardet==5.1.0
Requires-Dist: charset-normalizer==3.1.0
Requires-Dist: argparse
